mir/qualia/__init__.py
mir/qualia/__main__.py
mir/qualia/comment.py
mir/qualia/indent.py
mir/qualia/qualifier.py
mir.qualia-2.0.0.dist-info/DESCRIPTION.rst
mir.qualia-2.0.0.dist-info/METADATA
mir.qualia-2.0.0.dist-info/RECORD
mir.qualia-2.0.0.dist-info/WHEEL
mir.qualia-2.0.0.dist-info/entry_points.txt
mir.qualia-2.0.0.dist-info/metadata.json
mir.qualia-2.0.0.dist-info/top_level.txt
qualia/__init__.py
qualia/__main__.py
qualia/qualifier.py
